Metadata-Version: 2.1
Name: duration-check
Version: 1.0.4
Summary: Timeout and Duration decorator for python unittest.Testcase
Home-page: https://gitlab.com/devolive/pypi-packages/duration-check
Author: SECRET Olivier
Author-email: pypi-package-duration-check@devo.live
Classifier: Programming Language :: Python :: 3
Classifier: License :: OSI Approved :: GNU Lesser General Public License v3 or later (LGPLv3+)
Classifier: Operating System :: OS Independent
License-File: LICENSE
